Program
 SourceElements
  Statement
   VariableStatement
    keyword: K_VAR var [1:1:0:3]
    VariableDeclarationList
     VariableDeclaration
      Assignable
       id: a [1:5:4:5]
      Literal
       number: 1 "1" [1:9:8:9]
  Statement
   ExpressionStatement
    ExpressionSequence
     AssignmentExpression
      IdentifierExpression
       id: b [2:1:11:12]
      operator: T_ASSIGN = [2:3:13:14]
      Literal
       number: 2 "2" [2:5:15:16]
  Statement
   FunctionStatement
    AnonymousFunction
     FunctionDecl
      FunctionDeclaration
       keyword: K_FUNCTION function [3:1:18:26]
       id: add [3:10:27:30]
       FormalParameterList
        Assignable
         id: a [3:14:31:32]
        Assignable
         id: b [3:16:33:34]
       FunctionBody
        SourceElements
         Statement
          ReturnStatement
           keyword: K_RETURN return [3:20:37:43]
           ExpressionSequence
            AdditiveExpression
             IdentifierExpression
              id: a [3:27:44:45]
             operator: T_ADD + [3:28:45:46]
             IdentifierExpression
              id: b [3:29:46:47]
       operator: T_RBRACE } [3:31:48:49]
  Statement
   ReturnStatement
    keyword: K_RETURN return [4:1:50:56]
    ExpressionSequence
     PrimaryExpression
      IdentifierExpression
       id: add [4:8:57:60]
      PostfixExpression
       ArgumentsExpression
        Arguments
         Argument
          IdentifierExpression
           id: a [4:12:61:62]
          IdentifierExpression
           id: b [4:15:64:65]
         operator: T_RPARAN ) [4:16:65:66]
block [1:5:4:66]
 statement_var [1:5:4:9]
  id [1:5:4:9]
   id
    var [1:5:4:5]
     id: a
   init
    var [1:9:8:9]
     number: 1
 statement_exp [2:1:11:16]
  exp_seq [2:1:11:16]
   binop [2:1:11:16]
    exp1
     var_id [2:1:11:12]
      [GLOBAL] b
    op: T_ASSIGN [2:3:13:14]
    exp2
     var [2:5:15:16]
      number: 2
 statement_exp [3:1:18:49]
  exp_seq [3:1:18:49]
   code [3:1:18:49]
    name: add [3:10:27:30]
    args
     var_id [0:0:0:0]
      [LOCAL] a
     var_id [0:0:0:0]
      [LOCAL] b
    block [3:20:37:47]
     statement_return [3:20:37:47]
      exp_seq [3:27:44:47]
       binop [3:27:44:47]
        exp1
         var_id [3:27:44:45]
          a
        op: T_ADD [3:28:45:46]
        exp2
         var_id [3:29:46:47]
          b
 statement_return [4:1:50:66]
  exp_seq [4:8:57:66]
   call_function [4:8:57:66]
    obj
     var_id [4:8:57:60]
      [GLOBAL] add
    args
     var_id [4:12:61:62]
      [LOCAL] a
     var_id [4:15:64:65]
      [GLOBAL] b
--== Main Function ==--
C [#000] [NAME  ] a
C [#001] [NAME  ] add
C [#000] [NUMBER] 1.000000
C [#001] [NUMBER] 2.000000
C [#002] [FUNC  ] add | function add(a,b) {return a+b;}
C [#003] [STRING] add
C [0001:009]          0 LOAD_CONST                  0          (1)
C [0001:005]          1 STORE_NAME                  0          (a)
C [0001:005]          2 POP_TOP                                (a = 1)
C [0002:005]          3 LOAD_CONST                  1          (2)
C [0002:001]          4 STORE_GLOBAL                0          (b)
C [0002:001]          5 POP_TOP                                (b = 2)
C [0003:010]          6 LOAD_CONST                  2          (add)
C [0003:010]          7 LOAD_CONST                  3          (add)
C [0003:001]          8 MAKE_FUNCTION               0          (function add(a,b) {return a+b;})
C [0003:010]          9 STORE_NAME                  1          (add)
C [0003:001]         10 POP_TOP                                (function add(a,b) {return a+b;})
C [0004:008]         11 LOAD_GLOBAL                 1          (add)
C [0004:012]         12 LOAD_NAME                   0          (a)
C [0004:015]         13 LOAD_GLOBAL                 0          (b)
C [0004:008]         14 CALL_FUNCTION               2          (add(a, b))
C [0004:001]         15 RETURN_VALUE                           (return add(a, b))
--== Function: "add" ==--
C [#000] [NAME  ] a
C [#001] [NAME  ] b
C [0003:027]          0 LOAD_FAST                   0          (a)
C [0003:029]          1 LOAD_FAST                   1          (b)
C [0003:027]          2 BINARY_ADD                             (a+b)
C [0003:020]          3 RETURN_VALUE                           (return a+b)
R [0000] [0001:009]          0 LOAD_CONST                  0          (1)
============================================================
**** Stack [00EF986C] "UNKNOWN"
   1 | [00FDB020] number: 1
------------------------------------------------------------
 GC  | [00FDB020] Mark: 1, number: 1
############################################################
R [0001] [0001:005]          1 STORE_NAME                  0          (a)
============================================================
**** Stack [00EF986C] "UNKNOWN"
   1 | [00FDB020] number: 1
------------------------------------------------------------
 Env | [00FDB020] "a" number: 1
------------------------------------------------------------
 GC  | [00FDB020] Mark: 2, number: 1
############################################################
R [0002] [0001:005]          2 POP_TOP                                (a = 1)
**** Stack [00EF986C] "UNKNOWN"
------------------------------------------------------------
 Env | [00FDB020] "a" number: 1
------------------------------------------------------------
 GC  | [00FDB020] Mark: 2, number: 1
############################################################
R [0003] [0002:005]          3 LOAD_CONST                  1          (2)
============================================================
**** Stack [00EF986C] "UNKNOWN"
   1 | [00FDB170] number: 2
------------------------------------------------------------
 Env | [00FDB020] "a" number: 1
------------------------------------------------------------
 GC  | [00FDB020] Mark: 2, number: 1
 GC  | [00FDB170] Mark: 1, number: 2
############################################################
R [0004] [0002:001]          4 STORE_GLOBAL                0          (b)
============================================================
**** Stack [00EF986C] "UNKNOWN"
   1 | [00FDB170] number: 2
------------------------------------------------------------
 Env | [00FDB170] "b" number: 2
 Env | [00FDB020] "a" number: 1
------------------------------------------------------------
 GC  | [00FDB020] Mark: 2, number: 1
 GC  | [00FDB170] Mark: 2, number: 2
############################################################
R [0005] [0002:001]          5 POP_TOP                                (b = 2)
**** Stack [00EF986C] "UNKNOWN"
------------------------------------------------------------
 Env | [00FDB170] "b" number: 2
 Env | [00FDB020] "a" number: 1
------------------------------------------------------------
 GC  | [00FDB020] Mark: 2, number: 1
 GC  | [00FDB170] Mark: 2, number: 2
############################################################
R [0006] [0003:010]          6 LOAD_CONST                  2          (add)
============================================================
**** Stack [00EF986C] "UNKNOWN"
   1 | [010445AC] function: add
------------------------------------------------------------
 Env | [00FDB170] "b" number: 2
 Env | [00FDB020] "a" number: 1
------------------------------------------------------------
 GC  | [00FDB020] Mark: 2, number: 1
 GC  | [00FDB170] Mark: 2, number: 2
 GC  | [010445AC] Mark: 1, function: add
############################################################
R [0007] [0003:010]          7 LOAD_CONST                  3          (add)
============================================================
**** Stack [00EF986C] "UNKNOWN"
   2 | [01037E3C] string: add
   1 | [010445AC] function: add
------------------------------------------------------------
 Env | [00FDB170] "b" number: 2
 Env | [00FDB020] "a" number: 1
------------------------------------------------------------
 GC  | [00FDB020] Mark: 2, number: 1
 GC  | [00FDB170] Mark: 2, number: 2
 GC  | [010445AC] Mark: 1, function: add
 GC  | [01037E3C] Mark: 1, string: add
############################################################
R [0008] [0003:001]          8 MAKE_FUNCTION               0          (function add(a,b) {return a+b;})
============================================================
**** Stack [00EF986C] "UNKNOWN"
   1 | [010445AC] function: add
------------------------------------------------------------
 Env | [00FDB170] "b" number: 2
 Env | [00FDB020] "a" number: 1
------------------------------------------------------------
 GC  | [00FDB020] Mark: 2, number: 1
 GC  | [00FDB170] Mark: 2, number: 2
 GC  | [010445AC] Mark: 1, function: add
 GC  | [01037E3C] Mark: 0, string: add
############################################################
R [0009] [0003:010]          9 STORE_NAME                  1          (add)
============================================================
**** Stack [00EF986C] "UNKNOWN"
   1 | [010445AC] function: add
------------------------------------------------------------
 Env | [00FDB170] "b" number: 2
 Env | [010445AC] "add" function: add
 Env | [00FDB020] "a" number: 1
------------------------------------------------------------
 GC  | [00FDB020] Mark: 2, number: 1
 GC  | [00FDB170] Mark: 2, number: 2
 GC  | [010445AC] Mark: 2, function: add
############################################################
R [0010] [0003:001]         10 POP_TOP                                (function add(a,b) {return a+b;})
**** Stack [00EF986C] "UNKNOWN"
------------------------------------------------------------
 Env | [00FDB170] "b" number: 2
 Env | [010445AC] "add" function: add
 Env | [00FDB020] "a" number: 1
------------------------------------------------------------
 GC  | [00FDB020] Mark: 2, number: 1
 GC  | [00FDB170] Mark: 2, number: 2
 GC  | [010445AC] Mark: 2, function: add
############################################################
R [0011] [0004:008]         11 LOAD_GLOBAL                 1          (add)
============================================================
**** Stack [00EF986C] "UNKNOWN"
   1 | [010445AC] function: add
------------------------------------------------------------
 Env | [00FDB170] "b" number: 2
 Env | [010445AC] "add" function: add
 Env | [00FDB020] "a" number: 1
------------------------------------------------------------
 GC  | [00FDB020] Mark: 2, number: 1
 GC  | [00FDB170] Mark: 2, number: 2
 GC  | [010445AC] Mark: 2, function: add
############################################################
R [0012] [0004:012]         12 LOAD_NAME                   0          (a)
============================================================
**** Stack [00EF986C] "UNKNOWN"
   2 | [00FDB020] number: 1
   1 | [010445AC] function: add
------------------------------------------------------------
 Env | [00FDB170] "b" number: 2
 Env | [010445AC] "add" function: add
 Env | [00FDB020] "a" number: 1
------------------------------------------------------------
 GC  | [00FDB020] Mark: 2, number: 1
 GC  | [00FDB170] Mark: 2, number: 2
 GC  | [010445AC] Mark: 2, function: add
############################################################
R [0013] [0004:015]         13 LOAD_GLOBAL                 0          (b)
============================================================
**** Stack [00EF986C] "UNKNOWN"
   3 | [00FDB170] number: 2
   2 | [00FDB020] number: 1
   1 | [010445AC] function: add
------------------------------------------------------------
 Env | [00FDB170] "b" number: 2
 Env | [010445AC] "add" function: add
 Env | [00FDB020] "a" number: 1
------------------------------------------------------------
 GC  | [00FDB020] Mark: 2, number: 1
 GC  | [00FDB170] Mark: 2, number: 2
 GC  | [010445AC] Mark: 2, function: add
############################################################
R [0014] [0004:008]         14 CALL_FUNCTION               2          (add(a, b))
**** Stack [00EF9A9C] "add"
------------------------------------------------------------
 Env | [00FDB170] "b" number: 2
 Env | [00FDB020] "a" number: 1
------------------------------------------------------------
**** Stack [00EF986C] "UNKNOWN"
------------------------------------------------------------
 Env | [00FDB170] "b" number: 2
 Env | [010445AC] "add" function: add
 Env | [00FDB020] "a" number: 1
------------------------------------------------------------
 GC  | [00FDB020] Mark: 2, number: 1
 GC  | [00FDB170] Mark: 2, number: 2
 GC  | [010445AC] Mark: 2, function: add
############################################################
R [0000] [0003:027]          0 LOAD_FAST                   0          (a)
**** Stack [00EF9A9C] "add"
   1 | [00FDB020] number: 1
------------------------------------------------------------
 Env | [00FDB170] "b" number: 2
 Env | [00FDB020] "a" number: 1
------------------------------------------------------------
**** Stack [00EF986C] "UNKNOWN"
------------------------------------------------------------
 Env | [00FDB170] "b" number: 2
 Env | [010445AC] "add" function: add
 Env | [00FDB020] "a" number: 1
------------------------------------------------------------
 GC  | [00FDB020] Mark: 2, number: 1
 GC  | [00FDB170] Mark: 2, number: 2
 GC  | [010445AC] Mark: 2, function: add
############################################################
R [0001] [0003:029]          1 LOAD_FAST                   1          (b)
**** Stack [00EF9A9C] "add"
   2 | [00FDB170] number: 2
   1 | [00FDB020] number: 1
------------------------------------------------------------
 Env | [00FDB170] "b" number: 2
 Env | [00FDB020] "a" number: 1
------------------------------------------------------------
**** Stack [00EF986C] "UNKNOWN"
------------------------------------------------------------
 Env | [00FDB170] "b" number: 2
 Env | [010445AC] "add" function: add
 Env | [00FDB020] "a" number: 1
------------------------------------------------------------
 GC  | [00FDB020] Mark: 2, number: 1
 GC  | [00FDB170] Mark: 2, number: 2
 GC  | [010445AC] Mark: 2, function: add
############################################################
R [0002] [0003:027]          2 BINARY_ADD                             (a+b)
**** Stack [00EF9A9C] "add"
   1 | [00FDBBC0] number: 3
------------------------------------------------------------
 Env | [00FDB170] "b" number: 2
 Env | [00FDB020] "a" number: 1
------------------------------------------------------------
**** Stack [00EF986C] "UNKNOWN"
------------------------------------------------------------
 Env | [00FDB170] "b" number: 2
 Env | [010445AC] "add" function: add
 Env | [00FDB020] "a" number: 1
------------------------------------------------------------
 GC  | [00FDB020] Mark: 2, number: 1
 GC  | [00FDB170] Mark: 2, number: 2
 GC  | [010445AC] Mark: 2, function: add
 GC  | [00FDBBC0] Mark: 1, number: 3
############################################################
R [0003] [0003:020]          3 RETURN_VALUE                           (return a+b)
**** Stack [00EF9A9C] "add"
   1 | [00FDBBC0] number: 3
------------------------------------------------------------
 Env | [00FDB170] "b" number: 2
 Env | [00FDB020] "a" number: 1
------------------------------------------------------------
**** Stack [00EF986C] "UNKNOWN"
------------------------------------------------------------
 Env | [00FDB170] "b" number: 2
 Env | [010445AC] "add" function: add
 Env | [00FDB020] "a" number: 1
------------------------------------------------------------
 GC  | [00FDB020] Mark: 2, number: 1
 GC  | [00FDB170] Mark: 2, number: 2
 GC  | [010445AC] Mark: 2, function: add
 GC  | [00FDBBC0] Mark: 1, number: 3
############################################################
R [0015] [0004:001]         15 RETURN_VALUE                           (return add(a, b))
============================================================
**** Stack [00EF986C] "UNKNOWN"
   1 | [00FDBBC0] number: 3
------------------------------------------------------------
 Env | [00FDB170] "b" number: 2
 Env | [010445AC] "add" function: add
 Env | [00FDB020] "a" number: 1
------------------------------------------------------------
 GC  | [00FDB020] Mark: 2, number: 1
 GC  | [00FDB170] Mark: 2, number: 2
 GC  | [010445AC] Mark: 2, function: add
 GC  | [00FDBBC0] Mark: 1, number: 3
############################################################
number: 3
