Program
 SourceElements
  Statement
   VariableStatement
    keyword: K_VAR var [1:1:0:3]
    VariableDeclarationList
     VariableDeclaration
      Assignable
       id: a [1:5:4:5]
      Literal
       number: 1 "1" [1:9:8:9]
     VariableDeclaration
      Assignable
       id: b [1:12:11:12]
      Literal
       number: 2 "2" [1:16:15:16]
  Statement
   ReturnStatement
    keyword: K_RETURN return [2:1:18:24]
    ExpressionSequence
     PrimaryExpression
      ParenthesizedExpression
       operator: T_LPARAN ( [2:8:25:26]
       ExpressionSequence
        AnonymousFunction
         ArrowFunction
          ArrowFunctionParameters
           id: a [2:9:26:27]
          ArrowFunctionBody
           AnonymousFunction
            ArrowFunction
             ArrowFunctionParameters
              id: b [2:14:31:32]
             ArrowFunctionBody
              AdditiveExpression
               IdentifierExpression
                id: a [2:19:36:37]
               operator: T_ADD + [2:20:37:38]
               IdentifierExpression
                id: b [2:21:38:39]
       operator: T_RPARAN ) [2:22:39:40]
      PostfixExpression
       ArgumentsExpression
        Arguments
         Argument
          IdentifierExpression
           id: a [2:24:41:42]
         operator: T_RPARAN ) [2:25:42:43]
       ArgumentsExpression
        Arguments
         Argument
          IdentifierExpression
           id: b [2:27:44:45]
         operator: T_RPARAN ) [2:28:45:46]
block [1:5:4:46]
 statement_var [1:5:4:16]
  id [1:5:4:9]
   id
    var [1:5:4:5]
     id: a
   init
    var [1:9:8:9]
     number: 1
  id [1:12:11:16]
   id
    var [1:12:11:12]
     id: b
   init
    var [1:16:15:16]
     number: 2
 statement_return [2:1:18:46]
  exp_seq [2:9:25:46]
   call_function [2:9:25:46]
    obj
     call_function [2:9:25:43]
      obj
       code [2:9:25:40]
        args
         var_id [0:0:0:0]
          [LOCAL] a
        code [2:14:31:32]
         args
          var_id [0:0:0:0]
           [LOCAL] b
         binop [2:19:36:39]
          exp1
           var_id [2:19:36:37]
            [CLOSURE] a
          op: T_ADD [2:20:37:38]
          exp2
           var_id [2:21:38:39]
            [FAST] b
      args
       var_id [2:24:41:42]
        [LOCAL] a
    args
     var_id [2:27:44:45]
      [LOCAL] b
--== Main Function ==--
C [#000] [NAME  ] a
C [#001] [NAME  ] b
C [#000] [NUMBER] 1.000000
C [#001] [NUMBER] 2.000000
C [#002] [FUNC  ] <lambda> | (a => b => a+b)
C [#003] [STRING] <lambda>
C [0001:009]          0 LOAD_CONST                  0          (1)
C [0001:005]          1 STORE_NAME                  0          (a)
C [0001:005]          2 POP_TOP                                (a = 1)
C [0001:016]          3 LOAD_CONST                  1          (2)
C [0001:012]          4 STORE_NAME                  1          (b)
C [0001:012]          5 POP_TOP                                (b = 2)
C [0000:000]          6 LOAD_CONST                  2          (<lambda>)
C [0000:000]          7 LOAD_CONST                  3          (<lambda>)
C [0002:009]          8 MAKE_FUNCTION               0          ((a => b => a+b))
C [0002:024]          9 LOAD_NAME                   0          (a)
C [0002:009]         10 CALL_FUNCTION               1          ((a => b => a+b)(a))
C [0002:027]         11 LOAD_NAME                   1          (b)
C [0002:009]         12 CALL_FUNCTION               1          ((a => b => a+b)(a)(b))
C [0002:001]         13 RETURN_VALUE                           (return (a => b => a+b)(a)(b))
--== Function: "<lambda>" ==--
C [#000] [NAME  ] a
C [#000] [FUNC  ] <lambda>.<locals>.<lambda> | b
C [#001] [STRING] <lambda>.<locals>.<lambda>
C [0002:019]          0 LOAD_CLOSURE                0          (a)
C [0000:000]          1 BUILD_MAP                   1          (...)
C [0000:000]          2 LOAD_CONST                  0          (<lambda>)
C [0000:000]          3 LOAD_CONST                  1          (<lambda>.<locals>.<lambda>)
C [0002:014]          4 MAKE_FUNCTION               8          (b)
C [0000:000]          5 RETURN_VALUE                           (...)
--== Function: "<lambda>.<locals>.<lambda>" ==--
C [#000] [NAME  ] b
C [#000] [DEREF ] a
C [0002:019]          0 LOAD_DEREF                  0          (a)
C [0002:021]          1 LOAD_FAST                   0          (b)
C [0002:019]          2 BINARY_ADD                             (a+b)
C [0000:000]          3 RETURN_VALUE                           (...)
R [0000] [0001:009]          0 LOAD_CONST                  0          (1)
============================================================
**** Stack [00F34BBC] "UNKNOWN"
   1 | [01047258] number: 1
------------------------------------------------------------
 GC  | [01047258] Mark: 1, number: 1
############################################################
R [0001] [0001:005]          1 STORE_NAME                  0          (a)
============================================================
**** Stack [00F34BBC] "UNKNOWN"
   1 | [01047258] number: 1
------------------------------------------------------------
 Env | [01047258] "a" number: 1
------------------------------------------------------------
 GC  | [01047258] Mark: 2, number: 1
############################################################
R [0002] [0001:005]          2 POP_TOP                                (a = 1)
**** Stack [00F34BBC] "UNKNOWN"
------------------------------------------------------------
 Env | [01047258] "a" number: 1
------------------------------------------------------------
 GC  | [01047258] Mark: 2, number: 1
############################################################
R [0003] [0001:016]          3 LOAD_CONST                  1          (2)
============================================================
**** Stack [00F34BBC] "UNKNOWN"
   1 | [01046FB8] number: 2
------------------------------------------------------------
 Env | [01047258] "a" number: 1
------------------------------------------------------------
 GC  | [01047258] Mark: 2, number: 1
 GC  | [01046FB8] Mark: 1, number: 2
############################################################
R [0004] [0001:012]          4 STORE_NAME                  1          (b)
============================================================
**** Stack [00F34BBC] "UNKNOWN"
   1 | [01046FB8] number: 2
------------------------------------------------------------
 Env | [01046FB8] "b" number: 2
 Env | [01047258] "a" number: 1
------------------------------------------------------------
 GC  | [01047258] Mark: 2, number: 1
 GC  | [01046FB8] Mark: 2, number: 2
############################################################
R [0005] [0001:012]          5 POP_TOP                                (b = 2)
**** Stack [00F34BBC] "UNKNOWN"
------------------------------------------------------------
 Env | [01046FB8] "b" number: 2
 Env | [01047258] "a" number: 1
------------------------------------------------------------
 GC  | [01047258] Mark: 2, number: 1
 GC  | [01046FB8] Mark: 2, number: 2
############################################################
R [0006] [0000:000]          6 LOAD_CONST                  2          (<lambda>)
============================================================
**** Stack [00F34BBC] "UNKNOWN"
   1 | [0108E984] function: <lambda>
------------------------------------------------------------
 Env | [01046FB8] "b" number: 2
 Env | [01047258] "a" number: 1
------------------------------------------------------------
 GC  | [01047258] Mark: 2, number: 1
 GC  | [01046FB8] Mark: 2, number: 2
 GC  | [0108E984] Mark: 1, function: <lambda>
############################################################
R [0007] [0000:000]          7 LOAD_CONST                  3          (<lambda>)
============================================================
**** Stack [00F34BBC] "UNKNOWN"
   2 | [01097F84] string: <lambda>
   1 | [0108E984] function: <lambda>
------------------------------------------------------------
 Env | [01046FB8] "b" number: 2
 Env | [01047258] "a" number: 1
------------------------------------------------------------
 GC  | [01047258] Mark: 2, number: 1
 GC  | [01046FB8] Mark: 2, number: 2
 GC  | [0108E984] Mark: 1, function: <lambda>
 GC  | [01097F84] Mark: 1, string: <lambda>
############################################################
R [0008] [0002:009]          8 MAKE_FUNCTION               0          ((a => b => a+b))
============================================================
**** Stack [00F34BBC] "UNKNOWN"
   1 | [0108E984] function: <lambda>
------------------------------------------------------------
 Env | [01046FB8] "b" number: 2
 Env | [01047258] "a" number: 1
------------------------------------------------------------
 GC  | [01047258] Mark: 2, number: 1
 GC  | [01046FB8] Mark: 2, number: 2
 GC  | [0108E984] Mark: 1, function: <lambda>
 GC  | [01097F84] Mark: 0, string: <lambda>
############################################################
R [0009] [0002:024]          9 LOAD_NAME                   0          (a)
============================================================
**** Stack [00F34BBC] "UNKNOWN"
   2 | [01047258] number: 1
   1 | [0108E984] function: <lambda>
------------------------------------------------------------
 Env | [01046FB8] "b" number: 2
 Env | [01047258] "a" number: 1
------------------------------------------------------------
 GC  | [01047258] Mark: 2, number: 1
 GC  | [01046FB8] Mark: 2, number: 2
 GC  | [0108E984] Mark: 1, function: <lambda>
############################################################
R [0010] [0002:009]         10 CALL_FUNCTION               1          ((a => b => a+b)(a))
**** Stack [00F34C4C] "<lambda>"
------------------------------------------------------------
 Env | [01047258] "a" number: 1
------------------------------------------------------------
**** Stack [00F34BBC] "UNKNOWN"
------------------------------------------------------------
 Env | [01046FB8] "b" number: 2
 Env | [01047258] "a" number: 1
------------------------------------------------------------
 GC  | [01047258] Mark: 2, number: 1
 GC  | [01046FB8] Mark: 2, number: 2
 GC  | [0108E984] Mark: 0, function: <lambda>
############################################################
R [0000] [0002:019]          0 LOAD_CLOSURE                0          (a)
**** Stack [00F34C4C] "<lambda>"
   2 | [01047258] number: 1
   1 | [010983C4] string: a
------------------------------------------------------------
 Env | [01047258] "a" number: 1
------------------------------------------------------------
**** Stack [00F34BBC] "UNKNOWN"
------------------------------------------------------------
 Env | [01046FB8] "b" number: 2
 Env | [01047258] "a" number: 1
------------------------------------------------------------
 GC  | [01047258] Mark: 2, number: 1
 GC  | [01046FB8] Mark: 2, number: 2
 GC  | [010983C4] Mark: 1, string: a
############################################################
R [0001] [0000:000]          1 BUILD_MAP                   1          (...)
**** Stack [00F34C4C] "<lambda>"
   1 | [01097DC4] object:
a:  number: 1
------------------------------------------------------------
 Env | [01047258] "a" number: 1
------------------------------------------------------------
**** Stack [00F34BBC] "UNKNOWN"
------------------------------------------------------------
 Env | [01046FB8] "b" number: 2
 Env | [01047258] "a" number: 1
------------------------------------------------------------
 GC  | [01047258] Mark: 2, number: 1
 GC  | [01046FB8] Mark: 2, number: 2
 GC  | [010983C4] Mark: 0, string: a
 GC  | [01097DC4] Mark: 1, object:
a:  number: 1
############################################################
R [0002] [0000:000]          2 LOAD_CONST                  0          (<lambda>)
**** Stack [00F34C4C] "<lambda>"
   2 | [0108EA24] function: <lambda>.<locals>.<lambda>
   1 | [01097DC4] object:
a:  number: 1
------------------------------------------------------------
 Env | [01047258] "a" number: 1
------------------------------------------------------------
**** Stack [00F34BBC] "UNKNOWN"
------------------------------------------------------------
 Env | [01046FB8] "b" number: 2
 Env | [01047258] "a" number: 1
------------------------------------------------------------
 GC  | [01047258] Mark: 2, number: 1
 GC  | [01046FB8] Mark: 2, number: 2
 GC  | [01097DC4] Mark: 1, object:
a:  number: 1
 GC  | [0108EA24] Mark: 1, function: <lambda>.<locals>.<lambda>
############################################################
R [0003] [0000:000]          3 LOAD_CONST                  1          (<lambda>.<locals>.<lambda>)
**** Stack [00F34C4C] "<lambda>"
   3 | [01097C84] string: <lambda>.<locals>.<lambda>
   2 | [0108EA24] function: <lambda>.<locals>.<lambda>
   1 | [01097DC4] object:
a:  number: 1
------------------------------------------------------------
 Env | [01047258] "a" number: 1
------------------------------------------------------------
**** Stack [00F34BBC] "UNKNOWN"
------------------------------------------------------------
 Env | [01046FB8] "b" number: 2
 Env | [01047258] "a" number: 1
------------------------------------------------------------
 GC  | [01047258] Mark: 2, number: 1
 GC  | [01046FB8] Mark: 2, number: 2
 GC  | [01097DC4] Mark: 1, object:
a:  number: 1
 GC  | [0108EA24] Mark: 1, function: <lambda>.<locals>.<lambda>
 GC  | [01097C84] Mark: 1, string: <lambda>.<locals>.<lambda>
############################################################
R [0004] [0002:014]          4 MAKE_FUNCTION               8          (b)
**** Stack [00F34C4C] "<lambda>"
   1 | [0108EA24] function: <lambda>.<locals>.<lambda>
------------------------------------------------------------
 Env | [01047258] "a" number: 1
------------------------------------------------------------
**** Stack [00F34BBC] "UNKNOWN"
------------------------------------------------------------
 Env | [01046FB8] "b" number: 2
 Env | [01047258] "a" number: 1
------------------------------------------------------------
 GC  | [01047258] Mark: 2, number: 1
 GC  | [01046FB8] Mark: 2, number: 2
 GC  | [01097DC4] Mark: 1, object:
a:  number: 1
 GC  | [0108EA24] Mark: 1, function: <lambda>.<locals>.<lambda>
 GC  | [01097C84] Mark: 0, string: <lambda>.<locals>.<lambda>
############################################################
R [0005] [0000:000]          5 RETURN_VALUE                           (...)
**** Stack [00F34C4C] "<lambda>"
   1 | [0108EA24] function: <lambda>.<locals>.<lambda>
------------------------------------------------------------
 Env | [01047258] "a" number: 1
------------------------------------------------------------
**** Stack [00F34BBC] "UNKNOWN"
------------------------------------------------------------
 Env | [01046FB8] "b" number: 2
 Env | [01047258] "a" number: 1
------------------------------------------------------------
 GC  | [01047258] Mark: 2, number: 1
 GC  | [01046FB8] Mark: 2, number: 2
 GC  | [01097DC4] Mark: 1, object:
a:  number: 1
 GC  | [0108EA24] Mark: 1, function: <lambda>.<locals>.<lambda>
############################################################
R [0011] [0002:027]         11 LOAD_NAME                   1          (b)
============================================================
**** Stack [00F34BBC] "UNKNOWN"
   2 | [01046FB8] number: 2
   1 | [0108EA24] function: <lambda>.<locals>.<lambda>
------------------------------------------------------------
 Env | [01046FB8] "b" number: 2
 Env | [01047258] "a" number: 1
------------------------------------------------------------
 GC  | [01047258] Mark: 2, number: 1
 GC  | [01046FB8] Mark: 2, number: 2
 GC  | [01097DC4] Mark: 1, object:
a:  number: 1
 GC  | [0108EA24] Mark: 1, function: <lambda>.<locals>.<lambda>
############################################################
R [0012] [0002:009]         12 CALL_FUNCTION               1          ((a => b => a+b)(a)(b))
**** Stack [00F34D6C] "<lambda>.<locals>.<lambda>"
------------------------------------------------------------
 Env | [01046FB8] "b" number: 2
------------------------------------------------------------
**** Stack [00F34BBC] "UNKNOWN"
------------------------------------------------------------
 Env | [01046FB8] "b" number: 2
 Env | [01047258] "a" number: 1
------------------------------------------------------------
 GC  | [01047258] Mark: 2, number: 1
 GC  | [01046FB8] Mark: 2, number: 2
 GC  | [01097DC4] Mark: 0, object:
a:  number: 1
 GC  | [0108EA24] Mark: 0, function: <lambda>.<locals>.<lambda>
############################################################
R [0000] [0002:019]          0 LOAD_DEREF                  0          (a)
**** Stack [00F34D6C] "<lambda>.<locals>.<lambda>"
   1 | [01047258] number: 1
------------------------------------------------------------
 Env | [01046FB8] "b" number: 2
------------------------------------------------------------
**** Stack [00F34BBC] "UNKNOWN"
------------------------------------------------------------
 Env | [01046FB8] "b" number: 2
 Env | [01047258] "a" number: 1
------------------------------------------------------------
 GC  | [01047258] Mark: 1, number: 1
 GC  | [01046FB8] Mark: 2, number: 2
############################################################
R [0001] [0002:021]          1 LOAD_FAST                   0          (b)
**** Stack [00F34D6C] "<lambda>.<locals>.<lambda>"
   2 | [01046FB8] number: 2
   1 | [01047258] number: 1
------------------------------------------------------------
 Env | [01046FB8] "b" number: 2
------------------------------------------------------------
**** Stack [00F34BBC] "UNKNOWN"
------------------------------------------------------------
 Env | [01046FB8] "b" number: 2
 Env | [01047258] "a" number: 1
------------------------------------------------------------
 GC  | [01047258] Mark: 1, number: 1
 GC  | [01046FB8] Mark: 2, number: 2
############################################################
R [0002] [0002:019]          2 BINARY_ADD                             (a+b)
**** Stack [00F34D6C] "<lambda>.<locals>.<lambda>"
   1 | [01047798] number: 3
------------------------------------------------------------
 Env | [01046FB8] "b" number: 2
------------------------------------------------------------
**** Stack [00F34BBC] "UNKNOWN"
------------------------------------------------------------
 Env | [01046FB8] "b" number: 2
 Env | [01047258] "a" number: 1
------------------------------------------------------------
 GC  | [01047258] Mark: 2, number: 1
 GC  | [01046FB8] Mark: 2, number: 2
 GC  | [01047798] Mark: 1, number: 3
############################################################
R [0003] [0000:000]          3 RETURN_VALUE                           (...)
**** Stack [00F34D6C] "<lambda>.<locals>.<lambda>"
   1 | [01047798] number: 3
------------------------------------------------------------
 Env | [01046FB8] "b" number: 2
------------------------------------------------------------
**** Stack [00F34BBC] "UNKNOWN"
------------------------------------------------------------
 Env | [01046FB8] "b" number: 2
 Env | [01047258] "a" number: 1
------------------------------------------------------------
 GC  | [01047258] Mark: 2, number: 1
 GC  | [01046FB8] Mark: 2, number: 2
 GC  | [01047798] Mark: 1, number: 3
############################################################
R [0013] [0002:001]         13 RETURN_VALUE                           (return (a => b => a+b)(a)(b))
============================================================
**** Stack [00F34BBC] "UNKNOWN"
   1 | [01047798] number: 3
------------------------------------------------------------
 Env | [01046FB8] "b" number: 2
 Env | [01047258] "a" number: 1
------------------------------------------------------------
 GC  | [01047258] Mark: 2, number: 1
 GC  | [01046FB8] Mark: 2, number: 2
 GC  | [01047798] Mark: 1, number: 3
############################################################
number: 3
